codeforces/__init__.py
codeforces/__main__.py
codeforces/methods.py
codeforces/request.py
codeforces_cli-1.0.dist-info/LICENSE
codeforces_cli-1.0.dist-info/METADATA
codeforces_cli-1.0.dist-info/WHEEL
codeforces_cli-1.0.dist-info/entry_points.txt
codeforces_cli-1.0.dist-info/top_level.txt
codeforces_cli-1.0.dist-info/RECORD
