Metadata-Version: 2.1
Name: codeforces-cli
Version: 1.0
Summary: Command line interface for Codeforces
Home-page: https://github.com/aakashdinkar/codeforces-cli
Author: Aakash Dinkar
Author-email: aakashdinkar1307@gmail.com
License: MIT
Platform: UNKNOWN
Classifier: License :: OSI Approved :: MIT License
Classifier: Programming Language :: Python :: 3.6
Classifier: Programming Language :: Python :: 3.7
Classifier: Programming Language :: Python :: 3.8
Requires-Dist: requests
Requires-Dist: tabulate
Requires-Dist: beautifulsoup4
